pyrtfsx/__init__.py
python_rtfsx-0.1.dist-info/LICENSE.txt
python_rtfsx-0.1.dist-info/METADATA
python_rtfsx-0.1.dist-info/WHEEL
python_rtfsx-0.1.dist-info/top_level.txt
python_rtfsx-0.1.dist-info/RECORD
