Metadata-Version: 2.1
Name: python-rtfsx
Version: 0.1
Summary: Simple Text File validator and parser for detecting errors in file
Home-page: UNKNOWN
Author: Hatch Family
License: UNKNOWN
Platform: UNKNOWN
Classifier: Programming Language :: Python :: 3
Classifier: License :: OSI Approved :: MIT License
Classifier: Operating System :: OS Independent
License-File: LICENSE.txt
